rclone/__init__.py
rclone/rclone.py
rclone-0.4.3.dist-info/LICENSE
rclone-0.4.3.dist-info/WHEEL
rclone-0.4.3.dist-info/METADATA
rclone-0.4.3.dist-info/RECORD
