Metadata-Version: 2.1
Name: rclone
Version: 0.4.3
Summary: Python wrapper for rclone
License: MIT
Author: Alyetama
Author-email: 56323389+Alyetama@users.noreply.github.com
Requires-Python: >=3.6,<4.0
Classifier: License :: OSI Approved :: MIT License
Classifier: Programming Language :: Python :: 3
Classifier: Programming Language :: Python :: 3.10
Classifier: Programming Language :: Python :: 3.6
Classifier: Programming Language :: Python :: 3.7
Classifier: Programming Language :: Python :: 3.8
Classifier: Programming Language :: Python :: 3.9
Requires-Dist: loguru (>=0.5.3)
Requires-Dist: tqdm (>=4.62.3)
